lastfm_stats/__init__.py
lastfm_stats/lastfm.py
lastfm_stats-0.2.1.dist-info/LICENSE.md
lastfm_stats-0.2.1.dist-info/METADATA
lastfm_stats-0.2.1.dist-info/WHEEL
lastfm_stats-0.2.1.dist-info/top_level.txt
lastfm_stats-0.2.1.dist-info/RECORD
